MANIFEST.in
README.md
setup.cfg
setup.py
iliasScraper/VERSION
iliasScraper/__init__.py
iliasScraper/auth_manager.py
iliasScraper/cli.py
iliasScraper/config.py
iliasScraper/controller.py
iliasScraper/download_handler.py
iliasScraper/file_parser.py
iliasScraper/ilias_exceptions.py
iliasScraper/login_handler.py
iliasScraper/request_handler.py
iliasScraper/scraper.py
iliasScraper.egg-info/PKG-INFO
iliasScraper.egg-info/SOURCES.txt
iliasScraper.egg-info/dependency_links.txt
iliasScraper.egg-info/entry_points.txt
iliasScraper.egg-info/requires.txt
iliasScraper.egg-info/top_level.txt