Metadata-Version: 2.1
Name: iliasScraper
Version: 0.1.6
Summary: scraper for ilias platform of of the uni constance
Home-page: https://github.com/MisterXY89/iliasScraper
Author: Tilman Kerl
Author-email: tilmankerl@protonmail.com
License: UNKNOWN
Keywords: scraper,ilias,constance
Platform: UNKNOWN
Requires-Python: >=3.6
